syft_simple_runner/__init__.py
syft_simple_runner/app.py
syft_simple_runner/app.py.backup
syft_simple_runner/cli.py
syft_simple_runner/models.py.backup
syft_simple_runner/runner.py
syft_simple_runner-0.2.2.dist-info/METADATA
syft_simple_runner-0.2.2.dist-info/WHEEL
syft_simple_runner-0.2.2.dist-info/entry_points.txt
syft_simple_runner-0.2.2.dist-info/licenses/LICENSE
syft_simple_runner-0.2.2.dist-info/RECORD
